janus_core/__init__.py
janus_core/calculations/base.py
janus_core/calculations/descriptors.py
janus_core/calculations/eos.py
janus_core/calculations/geom_opt.py
janus_core/calculations/md.py
janus_core/calculations/neb.py
janus_core/calculations/phonons.py
janus_core/calculations/single_point.py
janus_core/cli/descriptors.py
janus_core/cli/eos.py
janus_core/cli/geomopt.py
janus_core/cli/janus.py
janus_core/cli/md.py
janus_core/cli/neb.py
janus_core/cli/phonons.py
janus_core/cli/preprocess.py
janus_core/cli/singlepoint.py
janus_core/cli/train.py
janus_core/cli/types.py
janus_core/cli/utils.py
janus_core/helpers/janus_types.py
janus_core/helpers/log.py
janus_core/helpers/mlip_calculators.py
janus_core/helpers/stats.py
janus_core/helpers/struct_io.py
janus_core/helpers/utils.py
janus_core/processing/correlator.py
janus_core/processing/observables.py
janus_core/processing/post_process.py
janus_core/processing/symmetry.py
janus_core/training/preprocess.py
janus_core/training/train.py
janus_core-0.8.6.dist-info/WHEEL
janus_core-0.8.6.dist-info/entry_points.txt
janus_core-0.8.6.dist-info/METADATA
janus_core-0.8.6.dist-info/RECORD
