Metadata-Version: 2.3
Name: janus-core
Version: 0.8.6
Summary: Tools for machine learnt interatomic potentials
Author: Elliott Kasoar, Patrick Austin, Harvey Devereux, Kieran Harris, David Mason, Jacob Wilkins, Federica Zanca, Alin M. Elena
Classifier: Programming Language :: Python
Classifier: Programming Language :: Python :: 3.10
Classifier: Programming Language :: Python :: 3.11
Classifier: Programming Language :: Python :: 3.12
Classifier: Intended Audience :: Science/Research
Classifier: License :: OSI Approved :: BSD License
Classifier: Natural Language :: English
Classifier: Development Status :: 3 - Alpha
Requires-Dist: ase>=3.25,<4.0
Requires-Dist: click>=8.2.1,<9
Requires-Dist: codecarbon>=3.0.7,<4.0.0
Requires-Dist: numpy>=1.26.4,<3.0.0
Requires-Dist: phonopy>=2.39.0,<3.0.0
Requires-Dist: pymatgen>=2025.1.24
Requires-Dist: pyyaml>=6.0.1,<7.0.0
Requires-Dist: rich>=13.9.1,<14.0.0
Requires-Dist: seekpath>=1.9.7,<2.0.0
Requires-Dist: spglib>=2.3.0,<3.0.0
Requires-Dist: typer>=0.19.1,<1.0.0
Requires-Dist: typer-config>=1.4.2,<2.0.0
Requires-Dist: alignn==2024.5.27 ; sys_platform != 'win32' and extra == 'alignn'
Requires-Dist: torch==2.2 ; sys_platform != 'win32' and extra == 'alignn'
Requires-Dist: torchdata==0.7.1 ; sys_platform != 'win32' and extra == 'alignn'
Requires-Dist: janus-core[chgnet] ; extra == 'all'
Requires-Dist: janus-core[grace] ; extra == 'all'
Requires-Dist: janus-core[d3] ; extra == 'all'
Requires-Dist: janus-core[mace] ; extra == 'all'
Requires-Dist: janus-core[orb] ; extra == 'all'
Requires-Dist: janus-core[pet-mad] ; extra == 'all'
Requires-Dist: janus-core[plumed] ; extra == 'all'
Requires-Dist: janus-core[visualise] ; extra == 'all'
Requires-Dist: chgnet==0.4.2 ; extra == 'chgnet'
Requires-Dist: torch-dftd==0.5.1 ; extra == 'd3'
Requires-Dist: deepmd-kit==3.1.0 ; extra == 'dpa3'
Requires-Dist: fairchem-core==1.10.0 ; extra == 'fairchem'
Requires-Dist: tensorpotential==0.5.1 ; extra == 'grace'
Requires-Dist: matgl==1.1.3 ; sys_platform != 'win32' and extra == 'm3gnet'
Requires-Dist: torch==2.2 ; sys_platform != 'win32' and extra == 'm3gnet'
Requires-Dist: torchdata==0.7.1 ; sys_platform != 'win32' and extra == 'm3gnet'
Requires-Dist: mace-torch==0.3.14 ; extra == 'mace'
Requires-Dist: janus-core[d3] ; extra == 'mace'
Requires-Dist: mattersim==1.1.2 ; sys_platform != 'win32' and extra == 'mattersim'
Requires-Dist: nequip==0.14.0 ; extra == 'nequip'
Requires-Dist: orb-models==0.5.5 ; sys_platform != 'win32' and extra == 'orb'
Requires-Dist: pet-mad==1.3.1 ; sys_platform != 'win32' and extra == 'pet-mad'
Requires-Dist: plumed>=2.9.0,<3.0.0 ; sys_platform != 'win32' and extra == 'plumed'
Requires-Dist: sevenn==0.11.2.post1 ; extra == 'sevennet'
Requires-Dist: fairchem-core==2.3.0 ; extra == 'uma'
Requires-Dist: weas-widget>=0.1.26,<0.2 ; extra == 'visualise'
Requires-Python: >=3.10
Project-URL: Documentation, https://stfc.github.io/janus-core/
Project-URL: Repository, https://github.com/stfc/janus-core/
Provides-Extra: alignn
Provides-Extra: all
Provides-Extra: chgnet
Provides-Extra: d3
Provides-Extra: dpa3
Provides-Extra: fairchem
Provides-Extra: grace
Provides-Extra: m3gnet
Provides-Extra: mace
Provides-Extra: mattersim
Provides-Extra: nequip
Provides-Extra: orb
Provides-Extra: pet-mad
Provides-Extra: plumed
Provides-Extra: sevennet
Provides-Extra: uma
Provides-Extra: visualise
